dailysum/__init__.py
dailysum/__main__.py
dailysum/cli.py
dailysum/config.py
dailysum/github_summarizer.py
dailysum-0.0.1.dist-info/licenses/LICENSE
dailysum-0.0.1.dist-info/METADATA
dailysum-0.0.1.dist-info/WHEEL
dailysum-0.0.1.dist-info/entry_points.txt
dailysum-0.0.1.dist-info/top_level.txt
dailysum-0.0.1.dist-info/RECORD
