Metadata-Version: 2.4
Name: dailysum
Version: 0.0.1
Summary: A CLI tool that uses AI agents to generate daily work summaries from GitHub activity
Author-email: Mozilla AI <ai-engineering@mozilla.com>
License: MIT
Project-URL: Documentation, https://github.com/njbrake/dailysum
Project-URL: Issues, https://github.com/njbrake/dailysum/issues
Project-URL: Source, https://github.com/njbrake/dailysum
Keywords: ai,github,productivity,cli,agent,llm
Classifier: Development Status :: 4 - Beta
Classifier: Environment :: Console
Classifier: Intended Audience :: Developers
Classifier: License :: OSI Approved :: MIT License
Classifier: Operating System :: OS Independent
Classifier: Programming Language :: Python :: 3
Classifier: Programming Language :: Python :: 3.11
Classifier: Programming Language :: Python :: 3.12
Classifier: Topic :: Software Development :: Libraries :: Python Modules
Classifier: Topic :: Office/Business
Classifier: Topic :: Utilities
Requires-Python: >=3.11
License-File: LICENSE
Requires-Dist: any-agent>=0.1.0
Requires-Dist: any-llm-sdk
Requires-Dist: click>=8.0.0
Requires-Dist: rich>=13.0.0
Requires-Dist: toml>=0.10.0
Provides-Extra: dev
Requires-Dist: pytest<9,>=8; extra == "dev"
Requires-Dist: pytest-cov<7,>=6.2.1; extra == "dev"
Requires-Dist: pytest-asyncio>=0.26.0; extra == "dev"
Requires-Dist: pre-commit==4.3.0; extra == "dev"
Requires-Dist: pre-commit-uv==4.1.4; extra == "dev"
Requires-Dist: ruff; extra == "dev"
Requires-Dist: mypy; extra == "dev"
Requires-Dist: types-toml; extra == "dev"
Provides-Extra: docs
Requires-Dist: mkdocs; extra == "docs"
Requires-Dist: mkdocs-material; extra == "docs"
Requires-Dist: mkdocstrings-python; extra == "docs"
Dynamic: license-file
